{"name":"Ghost","maze":"@1  ##    ##    ##          C4C3          ##    ##    ##  @2/  B4    ##    ##    ########    ########    ##    ##    B3  /##    ##    ##    ##      ##    ##      ##    ##    ##    ##/    ##    ##    ####                    ####    ##    ##    /  ##    ##    ##    ##    ########    ##    ##    ##    ##  /      ##    ##        ##    ####    ##        ##    ##      /    ##    ##    ####    ##        ##    ####    ##    ##    /  ##    ##    ########    ##    ##    ########    ##    ##  /      ##    ##A1########            ########A2##    ##      /    ##    ####              ####              ####    ##    /  ##    ############################################    ##  /##    ##  ##  ##                            ##  ##  ##    ##/    ##    ##  ######  ################  ######  ##    ##    /  ##      ##          ##            ##      ##  ##      ##  /      ##  ##    ########  ##!4!3##                  ##      /      ##                    !2!1    ########    ##  ##      /  ##      ##  ##      ##    ####    ##          ##      ##  /    ##    ##  ######  ################  ######  ##    ##    /##    ##  ##  ##                            ##  ##  ##    ##/  ##    ############################################    ##  /    ##    ####              ####              ####    ##    /      ##    ##A3########            ########A4##    ##      /  ##    ##    ########    ##    ##    ########    ##    ##  /    ##    ##    ####    ##        ##    ####    ##    ##    /##    ##    ##        ##    ####    ##        ##    ##    ##/  ##    ##    ##    ##    ########    ##    ##    ##    ##  /    ##    ##    ####                    ####    ##    ##    /##    ##    ##    ##      ##    ##      ##    ##    ##    ##/  B2    ##    ##    ########    ########    ##    ##    B1  /@3  ##          ##          C2C1          ##          ##  @4/","forms":[{"id":"A","name":""},{"id":"B","name":""},{"id":"C","name":""}]}